turba/__init__.py
turba/__main__.py
turba/_core.py
turba/_main.py
turba/_objects.py
turba/_version.py
turba/py.typed
turba-0.2.1.dist-info/LICENSE
turba-0.2.1.dist-info/METADATA
turba-0.2.1.dist-info/WHEEL
turba-0.2.1.dist-info/entry_points.txt
turba-0.2.1.dist-info/RECORD
