Metadata-Version: 2.1
Name: turba
Version: 0.2.1
Summary: Turbocharged torrent scraper
Home-page: https://pypi.org/project/turba/
License: MIT
Keywords: download,scraper,torrent,transmission,web
Author: jshwi
Author-email: stephen@jshwisolutions.com
Maintainer: jshwi
Maintainer-email: stephen@jshwisolutions.com
Requires-Python: >=3.8,<4.0
Classifier: License :: OSI Approved :: MIT License
Classifier: Programming Language :: Python :: 3
Classifier: Programming Language :: Python :: 3.8
Classifier: Programming Language :: Python :: 3.9
Classifier: Programming Language :: Python :: 3.10
Classifier: Programming Language :: Python :: 3.11
Requires-Dist: appdirs (>=1.4.4,<2.0.0)
Requires-Dist: beautifulsoup4 (>=4.9.3,<5.0.0)
Requires-Dist: bencode.py (>=4.0.0,<5.0.0)
Requires-Dist: object-colors (>=2.1.0,<3.0.0)
Requires-Dist: transmission-rpc (>=3.2.1,<8.0.0)
Project-URL: Documentation, https://turba.readthedocs.io/en/latest
Project-URL: Repository, https://github.com/jshwi/turba
